cstat/__init__.py
cstat/command.py
cstat/connector.py
cstat/log.py
cstat/repl.py
cstat/utils.py
cstat/widgets.py
cstat/window.py
cstat-3.0.0.dist-info/DESCRIPTION.rst
cstat-3.0.0.dist-info/METADATA
cstat-3.0.0.dist-info/RECORD
cstat-3.0.0.dist-info/WHEEL
cstat-3.0.0.dist-info/entry_points.txt
cstat-3.0.0.dist-info/metadata.json
cstat-3.0.0.dist-info/top_level.txt
