Metadata-Version: 2.0
Name: cstat
Version: 3.0.0
Summary: A visual stat tool for CrateDB clusters
Home-page: https://github.com/chaudum/crate-top
Author: Christian Haudum
Author-email: christian.haudum@crate.io
License: Apache License 2.0
Platform: any
Classifier: Development Status :: 4 - Beta
Classifier: Intended Audience :: Developers
Classifier: License :: OSI Approved :: Apache Software License
Classifier: Operating System :: OS Independent
Classifier: Programming Language :: Python
Classifier: Programming Language :: Python :: 3
Classifier: Programming Language :: Python :: 3.5
Classifier: Programming Language :: Python :: 3.6
Requires-Dist: appdirs
Requires-Dist: aiopg
Requires-Dist: colorama
Requires-Dist: urwid
Provides-Extra: develop
Requires-Dist: pudb; extra == 'develop'
